mergr-0.2.0.dist-info/METADATA
mergr-0.2.0.dist-info/WHEEL
mergr-0.2.0.dist-info/licenses/LICENSE
mergr/__init__.py
mergr/_version.py
mergr/merger.py
mergr/py.typed
mergr-0.2.0.dist-info/RECORD
