Metadata-Version: 2.1
Name: mergr
Version: 0.2.0
Summary: Objects merging utility
Keywords: python
Author-Email: alxevvv <alxevvv@gmail.com>
License: MIT
Requires-Python: >=3.10
